wattile/@ic.code-workspace
wattile/__init__.py
wattile/configs/configs.json
wattile/data_processing.py
wattile/data_reading.py
wattile/entry_point.py
wattile/error.py
wattile/holidays.py
wattile/model_registry.py
wattile/models/__init__.py
wattile/models/alfa_ensemble_model.py
wattile/models/alfa_model.py
wattile/models/base_model.py
wattile/models/bravo_model.py
wattile/models/charlie_model.py
wattile/models/ffnn.py
wattile/models/lstm.py
wattile/models/rnn.py
wattile/models/utils.py
wattile/time_processing.py
wattile/util.py
wattile/visualization.py
wattile-0.3.1.dist-info/LICENSE
wattile-0.3.1.dist-info/METADATA
wattile-0.3.1.dist-info/WHEEL
wattile-0.3.1.dist-info/RECORD
