Metadata-Version: 2.1
Name: wattile
Version: 0.3.1
Summary: Probabilistic Deep Learning-based Forecasting of Building Energy ConsumptionProbabilistic Deep Learning-based Forecasting of Building Energy Consumption.
Home-page: https://github.com/NREL/Wattile
Author: Your Name
Author-email: you@example.com
Requires-Python: >=3.10,<3.13
Classifier: Programming Language :: Python :: 3
Classifier: Programming Language :: Python :: 3.10
Classifier: Programming Language :: Python :: 3.11
Classifier: Programming Language :: Python :: 3.12
Requires-Dist: Pillow (>=10.4,<10.5)
Requires-Dist: kaleido (==0.2.1)
Requires-Dist: matplotlib (>=3.9,<3.10)
Requires-Dist: mlflow (>=2.15.1,<3.0.0)
Requires-Dist: nbmake (>=1.5,<1.6)
Requires-Dist: numpy (>=1.26,<1.27)
Requires-Dist: pandas (>=2.2,<2.3)
Requires-Dist: plotly (>=5.23,<5.24)
Requires-Dist: psutil (>=6.0,<6.1)
Requires-Dist: scipy (>=1.14,<1.15)
Requires-Dist: seaborn (>=0.13,<0.14)
Requires-Dist: setuptools (>=73.0,<73.1)
Requires-Dist: tables (>=3.10,<3.11)
Requires-Dist: tensorboard (>=2.16,<2.17)
Requires-Dist: tensorboardX (==2.6)
Requires-Dist: torch (>=2.4,<2.5)
Requires-Dist: xarray (>=2024.7.0,<2024.8.0)
Project-URL: Repository, https://github.com/NREL/Wattile
